[
    {
    "display_name": null,
    "name_variants": null,
    "activity": [
      "hike trails",
      "watch t.v.",
      "play games",
      "ride bikes",
      "travel",
      "go to the movies",
      "hang out with friends",
      "eat out",
      "bowl"
    ],
    "food": [
      "pizza",
      "cheeseburger",
      "french fries",
      "ice cream",
      "queso",
      "bacon",
      "taco",
      "shake",
      "hot dog",
      "sushi",
      "cake",
      "lasagna",
      "chicken nuggets",
      "fried chicken"
    ],
    "restaurant": [
      "Cooper’s Old Time Pit Bar-B-Que",
      "Franklin Barbecue",
      "Gus Fried Chicken",
      "Din Ho BBQ",
      "P Terry's",
      "Casino El Camino",
      "East Side Kings",
      "P. Terry’s",
      "Uchi",
      "Justine’s",
      "Joe’s Bakery",
      "Uchiko",
      "Veracruz All-Natural",
      "Home Slice"
    ],
    "place": [
      "Ladybird Lake",
      "Barton Springs",
      "Lake Travis",
      "East Side",
      "South Congress",
      "Mueller Neighborhood",
      "Round Rock",
      "Cedar Park",
      "Wimberly",
      "Johnson City",
      "Lockhart",
      "Elgin"
    ],
    "friend": [
      "Willie Nelson",
      "Robert Earl Keen",
      "Guy Clark",
      "Billy Joe Shaver",
      "Buddy Holly",
      "Salena",
      "Stevie Ray Vaughan",
      "George Strait",
      "Erykah Badu",
      "Natalie Maines",
      "Roy Orbison",
      "Roky Erickson",
      "Daniel Johnston"
    ],
    "family": [
      "dad",
      "mom",
      "brother",
      "sister"
    ]
  },
  {
    "display_name": "Tom",
    "name_variants": ["Tom", "Thomas"],
    "activity": [
      "play drums",
      "play with your kids",
      "play video games",
      "watch a band",
      "play pool",
      "swim",
      "snorkel",
      "eat out",
      "wax poetic",
      "fish",
      "ski",
      "drink booze"
    ],
    "food": ["bad pizza", "eating", "pizza", "funyuns"],
    "restaurant": ["P. Terrys", "Swift's Attic", "Voodoo Donuts", "The Onion"],
    "place": [
      "Wimberly Texas",
      "Lockhart Texas",
      "Athens Georgia",
      "New York City",
      "San Francisco",
      "Portland Oregon"
    ],
    "friend": [
      "Chloe",
      "Felix",
      "Cory",
      "<phoneme alphabet='ipa' ph='leɪ.ni'>Lani</phoneme>",
      "Doug",
      "Gerber",
      "Wheaton",
      "Stephanie",
      "Karel",
      "Jeff",
      "Max",
      "Marc"
    ],
    "family": ["Mom", "Dad"]
  },
  {
    "display_name": "Morgan",
    "name_variants": ["Gerber", "Morgan"],
    "activity": [
      "dodgeball",
      "snowshoe",
      "play soccer",
      "drink",
      "garden",
      "painting dogs"
    ],
    "food": ["pizza", "chex-mix", "domino's"],
    "restaurant": ["Casino El Camino", "Clark's", "Portillo's"],
    "place": ["work", "home", "the big apple", "the river"],
    "friend": ["Stephanie", "Morgan", "Jeremy", "Savannah", "Cameron"],
    "family": ["Mom", "Dad"]
  }
]
